pate/PATE_metric.py
pate/PATE_utils.py
pate/__init__.py
PATE-0.1.1.dist-info/LICENSE
PATE-0.1.1.dist-info/METADATA
PATE-0.1.1.dist-info/WHEEL
PATE-0.1.1.dist-info/top_level.txt
PATE-0.1.1.dist-info/RECORD
