Metadata-Version: 2.1
Name: PATE
Version: 0.1.1
Summary: PATE: Proximity-Aware Time series anomaly Evaluation metric
Home-page: https://github.com/Raminghorbanii/PATE
Author: Ramin Ghorbani
Author-email: r.ghorbani@tudelft.nl
Classifier: Development Status :: 3 - Alpha
Classifier: Intended Audience :: Science/Research
Classifier: License :: OSI Approved :: MIT License
Classifier: Programming Language :: Python :: 3
Classifier: Programming Language :: Python :: 3.8
Requires-Python: >=3.8
License-File: LICENSE
Requires-Dist: joblib (==1.4.2)
Requires-Dist: numpy (==1.24.4)
Requires-Dist: packaging (==24.0)
Requires-Dist: pandas (==2.0.3)
Requires-Dist: patsy (==0.5.6)
Requires-Dist: python-dateutil (==2.9.0.post0)
Requires-Dist: pytz (==2024.1)
Requires-Dist: scikit-learn (==1.3.2)
Requires-Dist: scipy (==1.10.1)
Requires-Dist: six (==1.16.0)
Requires-Dist: statsmodels (==0.14.1)
Requires-Dist: threadpoolctl (==3.5.0)
Requires-Dist: tzdata (==2024.1)
